<?xml version='1.0' encoding='utf-8' ?>
<root>
<item>
 <name>
Preces kods: EA01A_30
Invertors Growatt 3 fāžu 3kW MOD 3000TL3-XH</name>
 <link>https://www.saulesparki.lv/product/solarais-invertors-growatt-3-fazu-mod-3000tl3-xh/</link>
 <price>1.161,58</price>
 <image>https://www.saulesparki.lv/wp-content/uploads/2022/11/MOD_3-15KTL3-X_-_Copy-removebg-preview.jpg</image>
 <category_full> INVERTORI &gt;&gt; MĀJSAIMNIECĪBU INVERTORI&gt;&gt; 3 FĀŽU MĀJSAIMNIECĪBU INVERTORI</category_full>
 <category_link>https://www.saulesparki.lv/veikals/invertori/majsaimniecibu-invertori/3-fazu-majsaimniecibu-invertori/</category_link>
 <brand>Growatt</brand>
 <model><![CDATA[3000TL3-XH]]></model> 
 <color>White</color> 
 <!-- <mpn>SM-G950x`F</mpn>
 <gtin>0644391356614,644391356614</gtin> -->
 <in_stock>1</in_stock>
 <used>0</used>
 <adult>no</adult>
</item>

</root>
